py_mob/__init__.py
py_mob/py_mob.py
py_mob-0.4.0.dist-info/LICENSE.txt
py_mob-0.4.0.dist-info/METADATA
py_mob-0.4.0.dist-info/WHEEL
py_mob-0.4.0.dist-info/top_level.txt
py_mob-0.4.0.dist-info/RECORD
