Metadata-Version: 2.1
Name: py_mob
Version: 0.4.0
Summary: Python Implementation of Monotonic Optimal Binning
Home-page: https://github.com/statcompute/py_mob
Author: WenSui Liu
Author-email: liuwensui@gmail.com
Classifier: Programming Language :: Python :: 3
Classifier: License :: OSI Approved :: MIT License
Classifier: Operating System :: OS Independent
License-File: LICENSE.txt
Requires-Dist: numpy
Requires-Dist: scipy
Requires-Dist: scikit-learn
Requires-Dist: tabulate
Requires-Dist: pandas
